nextdns/__init__.py
nextdns/const.py
nextdns/exceptions.py
nextdns/model.py
nextdns/py.typed
nextdns-4.1.0.dist-info/licenses/LICENSE
nextdns-4.1.0.dist-info/METADATA
nextdns-4.1.0.dist-info/WHEEL
nextdns-4.1.0.dist-info/top_level.txt
nextdns-4.1.0.dist-info/RECORD
